{
  "history": {
    "2026-06-05": {
      "date": "2026-06-05",
      "score": 75,
      "quality": "FAIR",
      "total": 22440,
      "total_str": "6h 14m",
      "deep": 4500,
      "deep_str": "1h 15m",
      "deep_pct": 20.1,
      "light": 15240,
      "light_str": "4h 14m",
      "light_pct": 67.9,
      "rem": 2700,
      "rem_str": "45m",
      "rem_pct": 12.0,
      "awake": 480,
      "awake_str": "8m",
      "avg_hr": 49.0,
      "avg_hrv": null,
      "hrv_status": null,
      "avg_stress": 17.0,
      "avg_spo2": null,
      "avg_respiration": 11.0,
      "resting_hr": 43,
      "body_battery_change": null
    },
    "2026-06-04": {
      "date": "2026-06-04",
      "score": 75,
      "quality": "FAIR",
      "total": 24718,
      "total_str": "6h 51m",
      "deep": 3840,
      "deep_str": "1h 4m",
      "deep_pct": 15.5,
      "light": 18300,
      "light_str": "5h 5m",
      "light_pct": 74.0,
      "rem": 2580,
      "rem_str": "43m",
      "rem_pct": 10.4,
      "awake": 900,
      "awake_str": "15m",
      "avg_hr": 50.0,
      "avg_hrv": null,
      "hrv_status": null,
      "avg_stress": 20.0,
      "avg_spo2": null,
      "avg_respiration": 12.0,
      "resting_hr": 43,
      "body_battery_change": null
    },
    "2026-06-03": {
      "date": "2026-06-03",
      "score": 81,
      "quality": "GOOD",
      "total": 24631,
      "total_str": "6h 50m",
      "deep": 4200,
      "deep_str": "1h 10m",
      "deep_pct": 17.1,
      "light": 15660,
      "light_str": "4h 21m",
      "light_pct": 63.6,
      "rem": 4800,
      "rem_str": "1h 20m",
      "rem_pct": 19.5,
      "awake": 240,
      "awake_str": "4m",
      "avg_hr": 47.0,
      "avg_hrv": null,
      "hrv_status": null,
      "avg_stress": 15.0,
      "avg_spo2": null,
      "avg_respiration": 12.0,
      "resting_hr": 41,
      "body_battery_change": null
    },
    "2026-06-02": {
      "date": "2026-06-02",
      "score": 77,
      "quality": "FAIR",
      "total": 30520,
      "total_str": "8h 28m",
      "deep": 3360,
      "deep_str": "56m",
      "deep_pct": 11.0,
      "light": 21300,
      "light_str": "5h 55m",
      "light_pct": 69.8,
      "rem": 5880,
      "rem_str": "1h 38m",
      "rem_pct": 19.3,
      "awake": 2520,
      "awake_str": "42m",
      "avg_hr": 47.0,
      "avg_hrv": null,
      "hrv_status": null,
      "avg_stress": 16.0,
      "avg_spo2": null,
      "avg_respiration": 12.0,
      "resting_hr": 41,
      "body_battery_change": null
    },
    "2026-06-01": {
      "date": "2026-06-01",
      "score": 61,
      "quality": "FAIR",
      "total": 16582,
      "total_str": "4h 36m",
      "deep": 4440,
      "deep_str": "1h 14m",
      "deep_pct": 26.8,
      "light": 9720,
      "light_str": "2h 42m",
      "light_pct": 58.6,
      "rem": 2460,
      "rem_str": "41m",
      "rem_pct": 14.8,
      "awake": 120,
      "awake_str": "2m",
      "avg_hr": 43.0,
      "avg_hrv": null,
      "hrv_status": null,
      "avg_stress": 10.0,
      "avg_spo2": null,
      "avg_respiration": 11.0,
      "resting_hr": 39,
      "body_battery_change": null
    },
    "2026-05-31": {
      "date": "2026-05-31",
      "score": 87,
      "quality": "GOOD",
      "total": 26280,
      "total_str": "7h 18m",
      "deep": 6360,
      "deep_str": "1h 46m",
      "deep_pct": 24.2,
      "light": 14700,
      "light_str": "4h 5m",
      "light_pct": 55.9,
      "rem": 5220,
      "rem_str": "1h 27m",
      "rem_pct": 19.9,
      "awake": 1020,
      "awake_str": "17m",
      "avg_hr": 43.0,
      "avg_hrv": null,
      "hrv_status": null,
      "avg_stress": 11.0,
      "avg_spo2": null,
      "avg_respiration": 11.0,
      "resting_hr": 39,
      "body_battery_change": null
    },
    "2026-05-30": {
      "date": "2026-05-30",
      "score": 81,
      "quality": "GOOD",
      "total": 22800,
      "total_str": "6h 20m",
      "deep": 5640,
      "deep_str": "1h 34m",
      "deep_pct": 24.7,
      "light": 9720,
      "light_str": "2h 42m",
      "light_pct": 42.6,
      "rem": 7440,
      "rem_str": "2h 4m",
      "rem_pct": 32.6,
      "awake": 0,
      "awake_str": "0m",
      "avg_hr": 42.0,
      "avg_hrv": null,
      "hrv_status": null,
      "avg_stress": 10.0,
      "avg_spo2": null,
      "avg_respiration": 10.0,
      "resting_hr": 38,
      "body_battery_change": null
    },
    "2026-06-06": {
      "date": "2026-06-06",
      "score": 62,
      "quality": "FAIR",
      "total": 29640,
      "total_str": "8h 14m",
      "deep": 1800,
      "deep_str": "30m",
      "deep_pct": 6.1,
      "light": 26700,
      "light_str": "7h 25m",
      "light_pct": 90.1,
      "rem": 1140,
      "rem_str": "19m",
      "rem_pct": 3.8,
      "awake": 600,
      "awake_str": "10m",
      "avg_hr": 55.0,
      "avg_hrv": null,
      "hrv_status": null,
      "avg_stress": 27.0,
      "avg_spo2": null,
      "avg_respiration": 13.0,
      "resting_hr": 45,
      "body_battery_change": null
    },
    "2026-06-07": {
      "date": "2026-06-07",
      "score": 64,
      "quality": "FAIR",
      "total": 25440,
      "total_str": "7h 4m",
      "deep": 4260,
      "deep_str": "1h 11m",
      "deep_pct": 16.7,
      "light": 20160,
      "light_str": "5h 36m",
      "light_pct": 79.2,
      "rem": 1020,
      "rem_str": "17m",
      "rem_pct": 4.0,
      "awake": 0,
      "awake_str": "0m",
      "avg_hr": 53.0,
      "avg_hrv": null,
      "hrv_status": null,
      "avg_stress": 21.0,
      "avg_spo2": null,
      "avg_respiration": 12.0,
      "resting_hr": 43,
      "body_battery_change": null
    },
    "2026-06-08": {
      "date": "2026-06-08",
      "score": 60,
      "quality": "FAIR",
      "total": 17157,
      "total_str": "4h 45m",
      "deep": 3540,
      "deep_str": "59m",
      "deep_pct": 20.6,
      "light": 12240,
      "light_str": "3h 24m",
      "light_pct": 71.3,
      "rem": 1380,
      "rem_str": "23m",
      "rem_pct": 8.0,
      "awake": 600,
      "awake_str": "10m",
      "avg_hr": 50.0,
      "avg_hrv": null,
      "hrv_status": null,
      "avg_stress": 14.0,
      "avg_spo2": null,
      "avg_respiration": 11.0,
      "resting_hr": 43,
      "body_battery_change": null
    }
  },
  "fetched_at": "2026-06-08T08:10:44"
}